Metadata-Version: 2.4
Name: fastapitempk
Version: 0.1.0
Summary: FastAPI project template generator
Author: Karimov
Requires-Python: >=3.10
